asyncsleepiq/__init__.py
asyncsleepiq/actuator.py
asyncsleepiq/api.py
asyncsleepiq/asyncsleepiq.py
asyncsleepiq/bed.py
asyncsleepiq/consts.py
asyncsleepiq/core_climate.py
asyncsleepiq/exceptions.py
asyncsleepiq/foot_warmer.py
asyncsleepiq/foundation.py
asyncsleepiq/light.py
asyncsleepiq/preset.py
asyncsleepiq/py.typed
asyncsleepiq/sleeper.py
asyncsleepiq/fuzion/actuator.py
asyncsleepiq/fuzion/bed.py
asyncsleepiq/fuzion/core_climate.py
asyncsleepiq/fuzion/foot_warmer.py
asyncsleepiq/fuzion/foundation.py
asyncsleepiq/fuzion/light.py
asyncsleepiq/fuzion/preset.py
asyncsleepiq/fuzion/sleeper.py
asyncsleepiq-1.6.1.dist-info/licenses/LICENSE
asyncsleepiq-1.6.1.dist-info/METADATA
asyncsleepiq-1.6.1.dist-info/WHEEL
asyncsleepiq-1.6.1.dist-info/top_level.txt
asyncsleepiq-1.6.1.dist-info/RECORD
