Metadata-Version: 2.4
Name: asyncsleepiq
Version: 1.6.1
Summary: ASync SleepIQ API
Home-page: http://github.com/kbickar/asyncsleepiq
Author: Keilin Bickar
Author-email: trumpetgod@gmail.com
License: MIT
Classifier: Programming Language :: Python :: 3
License-File: LICENSE
Requires-Dist: aiohttp; python_version >= "3.7"
Dynamic: author
Dynamic: author-email
Dynamic: classifier
Dynamic: description
Dynamic: description-content-type
Dynamic: home-page
Dynamic: license
Dynamic: license-file
Dynamic: requires-dist
Dynamic: summary
